biner/__init__.py
biner/module1/__init__.py
biner/module1/konversi.py
biner/module2/__init__.py
biner/module2/operasibiner.py
biner/module3/__init__.py
biner/module3/logika.py
biner/module4/__init__.py
biner/module4/change_and_search_bit.py
biner/module5/__init__.py
biner/module5/manipulasi.py
biner/module6/BitAnalysis.py
biner/module6/__init__.py
biner-0.0.3.dist-info/METADATA
biner-0.0.3.dist-info/WHEEL
biner-0.0.3.dist-info/top_level.txt
biner-0.0.3.dist-info/RECORD
