Metadata-Version: 2.1
Name: biner
Version: 0.0.3
Summary: package biner
Author: Kelompok 7B
Classifier: Programming Language :: Python :: 3
Classifier: License :: OSI Approved :: MIT License
Classifier: Operating System :: OS Independent
